whatsapp_wrapper/__init__.py
whatsapp_wrapper/audio_utilities.py
whatsapp_wrapper/configs.py
whatsapp_wrapper/core.py
whatsapp_wrapper/exceptions.py
whatsapp_wrapper/media_utilities.py
whatsapp_wrapper/message_object.py
whatsapp_wrapper/whatsapp_db.py
whatsapp_wrapper-0.1.6.dist-info/LICENSE
whatsapp_wrapper-0.1.6.dist-info/METADATA
whatsapp_wrapper-0.1.6.dist-info/WHEEL
whatsapp_wrapper-0.1.6.dist-info/top_level.txt
whatsapp_wrapper-0.1.6.dist-info/RECORD
