Metadata-Version: 2.1
Name: whatsapp-wrapper
Version: 0.1.6
Summary: Integration layer for WhatsApp Cloud API with Firestore for easy message storage and management.
Home-page: https://github.com/AntonioVentilii/whatsapp-wrapper
Author: Antonio Ventilii
Author-email: antonioventilii@gmail.com
License: MIT
Project-URL: Source Code, https://github.com/AntonioVentilii/whatsapp-wrapper
Project-URL: Issue Tracker, https://github.com/AntonioVentilii/whatsapp-wrapper/issues
Keywords: WhatsApp,Firestore,API,integration,messaging
Classifier: Development Status :: 3 - Alpha
Classifier: Intended Audience :: Developers
Classifier: Topic :: Software Development :: Libraries :: Python Modules
Classifier: License :: OSI Approved :: MIT License
Classifier: Programming Language :: Python :: 3
Classifier: Programming Language :: Python :: 3.8
Classifier: Programming Language :: Python :: 3.9
Classifier: Programming Language :: Python :: 3.10
Classifier: Programming Language :: Python :: 3.11
Requires-Python: >=3.8
License-File: LICENSE
Requires-Dist: requests
Requires-Dist: firestore-wrapper
Requires-Dist: pydub
Requires-Dist: ffmpeg-downloader
Requires-Dist: ffmpeg-python
